[{"time":"2018-05-07 20:15:32","user":"copy","pages":3,"copies":1,"printer":"HP LaserJet Professional P1109w 2","doc":"Microsoft Word - Documento1","pc":"DESKTOP-E2HM0CB","format":"Letter","height":"","width":"","duplex":"NOT DUPLEX","grayscale":"GRAYSCALE"},{"time":"2018-05-07 20:22:51","user":"copy","pages":13,"copies":1,"printer":"HP LaserJet Professional P1109w 2","doc":"Microsoft Word - Material Comp. Sensibilidad especial..doc","pc":"DESKTOP-E2HM0CB","format":"Letter","height":"","width":"","duplex":"NOT DUPLEX","grayscale":"GRAYSCALE"}]